CHANGES.rst
MANIFEST.in
README.rst
buildout.cfg
screenshot.png
setup.py
docs/LICENSE.GPL
docs/LICENSE.txt
plonetheme/__init__.py
plonetheme.aclark_twitter.egg-info/PKG-INFO
plonetheme.aclark_twitter.egg-info/SOURCES.txt
plonetheme.aclark_twitter.egg-info/dependency_links.txt
plonetheme.aclark_twitter.egg-info/entry_points.txt
plonetheme.aclark_twitter.egg-info/namespace_packages.txt
plonetheme.aclark_twitter.egg-info/not-zip-safe
plonetheme.aclark_twitter.egg-info/requires.txt
plonetheme.aclark_twitter.egg-info/top_level.txt
plonetheme/aclark_twitter/__init__.py
plonetheme/aclark_twitter/configure.zcml
plonetheme/aclark_twitter/profiles.zcml
plonetheme/aclark_twitter/skins.zcml
plonetheme/aclark_twitter/tests.py
plonetheme/aclark_twitter/browser/__init__.py
plonetheme/aclark_twitter/browser/configure.zcml
plonetheme/aclark_twitter/browser/interfaces.py
plonetheme/aclark_twitter/browser/viewlet.pt
plonetheme/aclark_twitter/browser/viewlets.py
plonetheme/aclark_twitter/browser/images/README.txt
plonetheme/aclark_twitter/browser/stylesheets/README.txt
plonetheme/aclark_twitter/browser/stylesheets/main.css
plonetheme/aclark_twitter/profiles/default/cssregistry.xml
plonetheme/aclark_twitter/profiles/default/metadata.xml
plonetheme/aclark_twitter/profiles/default/skins.xml
plonetheme/aclark_twitter/skins/plonetheme_aclark_twitter_custom_images/CONTENT.txt
plonetheme/aclark_twitter/skins/plonetheme_aclark_twitter_custom_images/logo.jpg
plonetheme/aclark_twitter/skins/plonetheme_aclark_twitter_custom_images/whiteboard-twitter.jpg
plonetheme/aclark_twitter/skins/plonetheme_aclark_twitter_custom_templates/CONTENT.txt
plonetheme/aclark_twitter/skins/plonetheme_aclark_twitter_styles/CONTENT.txt
plonetheme/aclark_twitter/skins/plonetheme_aclark_twitter_styles/ploneCustom.css.dtml