Metadata-Version: 1.1
Name: plonetheme.aclark-twitter
Version: 1.3
Summary: Complete silliness: make your Plone site look like Alex Clark's Twitter profile.
Home-page: https://github.com/collective/plonetheme.aclark_twitter/
Author: Alex Clark
Author-email: aclark@aclark.net
License: GPL
Keywords: web zope plone theme
Platform: UNKNOWN
Classifier: Framework :: Plone
Classifier: Programming Language :: Python
Classifier: Programming Language :: Python :: 2.7
Classifier: Topic :: Software Development :: Libraries :: Python Modules
